gpnpytorchtools/__init__.py
gpnpytorchtools/data.py
gpnpytorchtools/lightning.py
gpnpytorchtools/lossfunctions.py
gpnpytorchtools/models.py
gpnpytorchtools/utils.py
gpnpytorchtools-0.1.0.dist-info/LICENSE
gpnpytorchtools-0.1.0.dist-info/METADATA
gpnpytorchtools-0.1.0.dist-info/WHEEL
gpnpytorchtools-0.1.0.dist-info/top_level.txt
gpnpytorchtools-0.1.0.dist-info/RECORD
