Metadata-Version: 2.1
Name: gpnpytorchtools
Version: 0.1.0
Summary: A collection of pytorch tools created by GPN members
Home-page: https://github.com/nxdens/GPNPytorchTools/
Author: Linghai Wang
License-File: LICENSE
Requires-Dist: torch >=2.0.1
Requires-Dist: pytest >=7.1.0
Requires-Dist: numpy >=1.24.1
Requires-Dist: lightning >=2.0.1
Requires-Dist: pandas
Requires-Dist: scikit-learn
Requires-Dist: linearinit
Provides-Extra: test
Requires-Dist: pytest ; extra == 'test'
Requires-Dist: coverage ; extra == 'test'
Requires-Dist: flake8 ; extra == 'test'
Requires-Dist: black ; extra == 'test'
Requires-Dist: isort ; extra == 'test'
Requires-Dist: pytest-cov ; extra == 'test'
Requires-Dist: mypy ; extra == 'test'
Requires-Dist: gitchangelog ; extra == 'test'
Requires-Dist: mkdocs ; extra == 'test'
Requires-Dist: virtualenv ; extra == 'test'
